setup.py
can/__init__.py
can/adapters.py
can/datagram.py
can/frame.py
cvra_bootloader/__init__.py
cvra_bootloader/bootloader_flash.py
cvra_bootloader/change_id.py
cvra_bootloader/commands.py
cvra_bootloader/page.py
cvra_bootloader/read_config.py
cvra_bootloader/run_application.py
cvra_bootloader/utils.py
cvra_bootloader/write_config.py
cvra_bootloader.egg-info/PKG-INFO
cvra_bootloader.egg-info/SOURCES.txt
cvra_bootloader.egg-info/dependency_links.txt
cvra_bootloader.egg-info/entry_points.txt
cvra_bootloader.egg-info/requires.txt
cvra_bootloader.egg-info/top_level.txt